himig/__init__.py
himig/_audio_player.py
himig/_core.py
himig/constants.py
himig/melodies.py
himig-1.0.2.dist-info/licenses/LICENSE
himig-1.0.2.dist-info/METADATA
himig-1.0.2.dist-info/WHEEL
himig-1.0.2.dist-info/top_level.txt
himig-1.0.2.dist-info/RECORD
