Metadata-Version: 2.4
Name: himig
Version: 1.0.2
Summary: Python music synthesis module that lets you compose, play, and save melodies
Author: j-ncel
Project-URL: Homepage, https://github.com/j-ncel/himig
Project-URL: Repository, https://github.com/j-ncel/himig
Keywords: music,audio,synthesis,melody,Python
Classifier: Programming Language :: Python :: 3
Classifier: Operating System :: OS Independent
License-File: LICENSE
Requires-Dist: numpy
Dynamic: license-file
